primosPython/__init__.py
primosPython-1.0.dist-info/LICENSE
primosPython-1.0.dist-info/METADATA
primosPython-1.0.dist-info/WHEEL
primosPython-1.0.dist-info/top_level.txt
primosPython-1.0.dist-info/RECORD
